pyramid_resume_template_default/__init__.py
pyramid_resume_template_default/static/css/theme.css
pyramid_resume_template_default/static/favicon_io/about.txt
pyramid_resume_template_default/static/favicon_io/android-chrome-192x192.png
pyramid_resume_template_default/static/favicon_io/android-chrome-512x512.png
pyramid_resume_template_default/static/favicon_io/apple-touch-icon.png
pyramid_resume_template_default/static/favicon_io/favicon-16x16.png
pyramid_resume_template_default/static/favicon_io/favicon-32x32.png
pyramid_resume_template_default/static/favicon_io/favicon.ico
pyramid_resume_template_default/static/favicon_io/site.webmanifest
pyramid_resume_template_default/static/icomoon/fonts/icomoon.eot
pyramid_resume_template_default/static/icomoon/fonts/icomoon.svg
pyramid_resume_template_default/static/icomoon/fonts/icomoon.ttf
pyramid_resume_template_default/static/icomoon/fonts/icomoon.woff
pyramid_resume_template_default/static/icomoon/style.css
pyramid_resume_template_default/static/vendor/bootstrap/css/bootstrap-grid.css
pyramid_resume_template_default/static/vendor/bootstrap/css/bootstrap-grid.min.css
pyramid_resume_template_default/static/vendor/bootstrap/css/bootstrap-reboot.css
pyramid_resume_template_default/static/vendor/bootstrap/css/bootstrap-reboot.min.css
pyramid_resume_template_default/static/vendor/bootstrap/css/bootstrap.css
pyramid_resume_template_default/static/vendor/bootstrap/css/bootstrap.min.css
pyramid_resume_template_default/static/vendor/bootstrap/js/bootstrap.bundle.js
pyramid_resume_template_default/static/vendor/bootstrap/js/bootstrap.bundle.min.js
pyramid_resume_template_default/static/vendor/bootstrap/js/bootstrap.js
pyramid_resume_template_default/static/vendor/bootstrap/js/bootstrap.min.js
pyramid_resume_template_default/static/vendor/devicon/CONTRIBUTING.md
pyramid_resume_template_default/static/vendor/devicon/LICENSE
pyramid_resume_template_default/static/vendor/devicon/README.md
pyramid_resume_template_default-0.4.2.dist-info/LICENSE
pyramid_resume_template_default-0.4.2.dist-info/METADATA
pyramid_resume_template_default-0.4.2.dist-info/WHEEL
pyramid_resume_template_default-0.4.2.dist-info/entry_points.txt
pyramid_resume_template_default-0.4.2.dist-info/RECORD
