Metadata-Version: 2.1
Name: pyramid_resume_template_default
Version: 0.4.2
Summary: Default template for pyramid_resume
License: MIT
Author: Steve Locke
Author-email: steve@locke.codes
Requires-Python: >=3.9,<4.0
Classifier: Development Status :: 2 - Pre-Alpha
Classifier: Intended Audience :: Developers
Classifier: License :: OSI Approved :: MIT License
Classifier: Natural Language :: English
Classifier: Programming Language :: Python :: 3
Classifier: Programming Language :: Python :: 3.9
Classifier: Programming Language :: Python :: 3.10
Classifier: Programming Language :: Python :: 3.11
Classifier: Programming Language :: Python :: 3.12
Classifier: Programming Language :: Python :: 3.13
